bilichat_request-0.5.10.dist-info/METADATA
bilichat_request-0.5.10.dist-info/WHEEL
bilichat_request-0.5.10.dist-info/entry_points.txt
bilichat_request-0.5.10.dist-info/licenses/LICENSE
bilichat_request/__init__.py
bilichat_request/__main__.py
bilichat_request/account/__init__.py
bilichat_request/account/base.py
bilichat_request/account/cookie_cloud.py
bilichat_request/account/normal.py
bilichat_request/adapters/browser/__init__.py
bilichat_request/adapters/browser/browser_ctx.py
bilichat_request/adapters/browser/font.py
bilichat_request/adapters/browser/install_browser.py
bilichat_request/adapters/web/__init__.py
bilichat_request/api/__init__.py
bilichat_request/api/account.py
bilichat_request/api/base.py
bilichat_request/api/content.py
bilichat_request/api/subs.py
bilichat_request/api/tools.py
bilichat_request/compat.py
bilichat_request/config.py
bilichat_request/const.py
bilichat_request/exceptions.py
bilichat_request/functions/cookie_cloud.py
bilichat_request/functions/dynamic_content.py
bilichat_request/functions/render/column.py
bilichat_request/functions/render/dynamic.py
bilichat_request/functions/render/video/__init__.py
bilichat_request/functions/render/video/model/card.py
bilichat_request/functions/render/video/model/video.py
bilichat_request/functions/render/video/style_blue.py
bilichat_request/functions/subs/__init__.py
bilichat_request/functions/subs/dynamic/__init__.py
bilichat_request/functions/subs/dynamic/model.py
bilichat_request/functions/subs/live/__init__.py
bilichat_request/functions/subs/live/model.py
bilichat_request/functions/tools.py
bilichat_request/log.py
bilichat_request/main.py
bilichat_request/model/config.py
bilichat_request/static/style_blue/assets/business.png
bilichat_request/static/style_blue/assets/personal.png
bilichat_request/static/style_blue/assets/video_bottom.png
bilichat_request/static/style_blue/video-details.html
bilichat_request-0.5.10.dist-info/RECORD
