Metadata-Version: 2.1
Name: bilichat-request
Version: 0.5.10
Summary: Default template for PDM package
Author-Email: Well404 <well_404@outlook.com>
License: None
Requires-Python: <4.0,>=3.10
Requires-Dist: playwright>=1.48.0
Requires-Dist: httpx>=0.27.2
Requires-Dist: jinja2>=3.1.4
Requires-Dist: fastapi>=0.115.5
Requires-Dist: loguru>=0.7.2
Requires-Dist: sentry-sdk[fastapi]>=2.20.0
Requires-Dist: pypng>=0.20220715.0
Requires-Dist: uvicorn>=0.32.1
Requires-Dist: pytz>=2024.2
Requires-Dist: python-jose[cryptography]>=3.3.0
Requires-Dist: python-multipart>=0.0.19
Requires-Dist: pydantic>=2.10.3
Requires-Dist: bcrypt>=4.2.1
Requires-Dist: slowapi>=0.1.9
Requires-Dist: pycryptodomex>=3.21.0
Requires-Dist: qrcode>=8.0
Requires-Dist: pyyaml>=6.0.2
Requires-Dist: apscheduler>=3.11.0
Requires-Dist: cachetools>=5.5.1
Provides-Extra: dev
Requires-Dist: nonebot-plugin-htmlrender>=0.4.0; extra == "dev"
Requires-Dist: nonebot2[fastapi]>=2.4.0; extra == "dev"
Requires-Dist: nonebot-plugin-apscheduler>=0.5.0; extra == "dev"
